botconfig/__init__.py
botconfig/client.py
botconfig-1.0.1.dist-info/LICENSE
botconfig-1.0.1.dist-info/METADATA
botconfig-1.0.1.dist-info/WHEEL
botconfig-1.0.1.dist-info/top_level.txt
botconfig-1.0.1.dist-info/RECORD
