Metadata-Version: 2.1
Name: botconfig
Version: 1.0.1
Summary: A simple discord bot configuration utility
Home-page: UNKNOWN
Author: tag-epic
Author-email: tagepicuwu@gmail.com
License: UNKNOWN
Project-URL: GitHub, https://github.com/discollaboration/BotConfigLib
Project-URL: Website, https://config.farfrom.world
Platform: UNKNOWN
Requires-Dist: speedcord
